csst_ifs_gehong-3.1.0.dist-info/licenses/LICENSE
gehong/__init__.py
gehong/config.py
gehong/cube3d.py
gehong/map2d.py
gehong/spec1d.py
csst_ifs_gehong-3.1.0.dist-info/METADATA
csst_ifs_gehong-3.1.0.dist-info/WHEEL
csst_ifs_gehong-3.1.0.dist-info/top_level.txt
csst_ifs_gehong-3.1.0.dist-info/RECORD
