Metadata-Version: 2.4
Name: csst-ifs-gehong
Version: 3.1.0
Summary: Simulate realistic IFS datacubes for the CSST mission, including stellar population, ionized gas, and AGN spectra.
Home-page: https://github.com/fengshuai0210/csst-ifs-gehong
Author: Shuai Feng
Author-email: Shuai Feng <sfeng@hebtu.edu.cn>
License: MIT
Project-URL: Homepage, https://github.com/fengshuai0210/csst-ifs-gehong
Project-URL: Documentation, https://csst-ifs-gehong.readthedocs.io
Project-URL: Source, https://github.com/fengshuai0210/csst-ifs-gehong
Classifier: Development Status :: 4 - Beta
Classifier: Intended Audience :: Science/Research
Classifier: Topic :: Scientific/Engineering :: Astronomy
Classifier: License :: OSI Approved :: MIT License
Classifier: Programming Language :: Python :: 3
Classifier: Programming Language :: Python :: 3.8
Classifier: Programming Language :: Python :: 3.9
Classifier: Programming Language :: Python :: 3.10
Requires-Python: >=3.8
License-File: LICENSE
Requires-Dist: numpy
Requires-Dist: scipy
Requires-Dist: astropy
Requires-Dist: matplotlib
Dynamic: license-file
